[
  {
    "anonymous": false,
    "inputs": [
      {
        "indexed": true,
        "internalType": "address",
        "name": "token",
        "type": "address"
      },
      {
        "indexed": true,
        "internalType": "address",
        "name": "owner",
        "type": "address"
      },
      {
        "indexed": false,
        "internalType": "uint256",
        "name": "unlockTime",
        "type": "uint256"
      },
      {
        "indexed": false,
        "internalType": "uint256",
        "name": "lockMonths",
        "type": "uint256"
      },
      {
        "indexed": false,
        "internalType": "string",
        "name": "imageCid",
        "type": "string"
      }
    ],
    "name": "Launched",
    "type": "event"
  }
]
